inltk/__init__.py
inltk/config.py
inltk/const.py
inltk/download_assets.py
inltk/inltk.py
inltk/tokenizer.py
inltk/utils.py
inltk-0.9.dist-info/LICENSE
inltk-0.9.dist-info/METADATA
inltk-0.9.dist-info/WHEEL
inltk-0.9.dist-info/dependency_links.txt
inltk-0.9.dist-info/top_level.txt
inltk-0.9.dist-info/RECORD
